detect_languages/__init__.py
detect_languages/cli.py
detect_languages/detect.py
detect_languages/languages.py
detect_languages-0.1.0b3.dist-info/LICENSE
detect_languages-0.1.0b3.dist-info/METADATA
detect_languages-0.1.0b3.dist-info/WHEEL
detect_languages-0.1.0b3.dist-info/entry_points.txt
detect_languages-0.1.0b3.dist-info/top_level.txt
detect_languages-0.1.0b3.dist-info/RECORD
