Metadata-Version: 2.1
Name: detect-languages
Version: 0.1.0b3
Summary: This module discover the programming languages from a project/repository.
Home-page: https://github.com/alexgracianoarj/detect-languages
Author: Alex Graciano
Author-email: alexgracianoarj@gmail.com
License: MIT
Keywords: detect,programming,languages
Platform: any
Classifier: Development Status :: 4 - Beta
Classifier: License :: OSI Approved :: MIT License
Classifier: Programming Language :: Python
Classifier: Programming Language :: Python :: 3.7
Classifier: Programming Language :: Python :: 3.8
Classifier: Programming Language :: Python :: 3.9
Classifier: Programming Language :: Python :: 3.10
License-File: LICENSE
Requires-Dist: pygments (>=2.10.0)
Requires-Dist: jmespath (>=0.10.0)
Requires-Dist: click (>=8.0.3)
Requires-Dist: tabulate (>=0.8.9)
